idendrogram_streamlit_component/__init__.py
idendrogram_streamlit_component/frontend/.env
idendrogram_streamlit_component/frontend/.prettierrc
idendrogram_streamlit_component/frontend/package-lock.json
idendrogram_streamlit_component/frontend/package.json
idendrogram_streamlit_component/frontend/tsconfig.json
idendrogram_streamlit_component/frontend/build/asset-manifest.json
idendrogram_streamlit_component/frontend/build/bootstrap.min.css
idendrogram_streamlit_component/frontend/build/index.html
idendrogram_streamlit_component/frontend/build/precache-manifest.3e58ef497f3baec2986da47144229e50.js
idendrogram_streamlit_component/frontend/build/service-worker.js
idendrogram_streamlit_component/frontend/build/static/css/main.40e50dec.chunk.css
idendrogram_streamlit_component/frontend/build/static/css/main.40e50dec.chunk.css.map
idendrogram_streamlit_component/frontend/build/static/js/2.09402de2.chunk.js
idendrogram_streamlit_component/frontend/build/static/js/2.09402de2.chunk.js.LICENSE.txt
idendrogram_streamlit_component/frontend/build/static/js/2.09402de2.chunk.js.map
idendrogram_streamlit_component/frontend/build/static/js/main.b350a90c.chunk.js
idendrogram_streamlit_component/frontend/build/static/js/main.b350a90c.chunk.js.map
idendrogram_streamlit_component/frontend/build/static/js/runtime-main.ea7b20aa.js
idendrogram_streamlit_component/frontend/build/static/js/runtime-main.ea7b20aa.js.map
idendrogram_streamlit_component/frontend/public/bootstrap.min.css
idendrogram_streamlit_component/frontend/public/index.html
idendrogram_streamlit_component/frontend/src/idendro.css
idendrogram_streamlit_component/frontend/src/index.tsx
idendrogram_streamlit_component/frontend/src/react-app-env.d.ts
idendrogram_streamlit_component-0.2.5.dist-info/LICENSE
idendrogram_streamlit_component-0.2.5.dist-info/WHEEL
idendrogram_streamlit_component-0.2.5.dist-info/METADATA
idendrogram_streamlit_component-0.2.5.dist-info/RECORD
