Metadata-Version: 2.1
Name: idendrogram-streamlit-component
Version: 0.2.5
Summary: Bi-directional Streamlit component for creating interactive dendrograms
Keywords: dendrogram,hierarchical clustering,clustering,streamlit,D3
Author: Aurimas Racas
Requires-Python: >=3.8
Classifier: Programming Language :: Python :: 3
Classifier: License :: OSI Approved :: MIT License
Classifier: Operating System :: OS Independent
Requires-Dist: streamlit >= 1.0
Requires-Dist: idendrogram ; extra == "full"
Project-URL: Documentation, https://github.com/kamicollo/idendrogram-streamlit
Project-URL: Home, https://github.com/kamicollo/idendrogram-streamlit
Provides-Extra: full
